Metadata-Version: 1.1
Name: imagehash-cli
Version: 0.1.0
Summary: Image Hash Command Line Interface
Home-page: https://github.com/lunardog/imagehash-cli
Author: Leszek Rybicki
Author-email: leszek-rybicki@cookpad.com
License: MIT
Download-URL: https://github.com/lunardog/imagehash-cli/archive/0.1.0.tar.gz
Platform: any
Classifier: Development Status :: 4 - Beta
Classifier: Environment :: Console
Classifier: Intended Audience :: Developers
Classifier: License :: OSI Approved :: BSD License
Classifier: Operating System :: POSIX
Classifier: Operating System :: MacOS
Classifier: Operating System :: Unix
Classifier: Operating System :: Microsoft :: Windows
Classifier: Programming Language :: Python
Classifier: Programming Language :: Python :: 2
Classifier: Programming Language :: Python :: 3
Classifier: Topic :: Software Development :: Libraries :: Python Modules
